myra_eucaptcha_django/__init__.py
myra_eucaptcha_django/admin.py
myra_eucaptcha_django/apps.py
myra_eucaptcha_django/fields.py
myra_eucaptcha_django/models.py
myra_eucaptcha_django/settings.py
myra_eucaptcha_django/validators.py
myra_eucaptcha_django/widgets.py
myra_eucaptcha_django/migrations/0001_initial.py
myra_eucaptcha_django/migrations/__init__.py
myra_eucaptcha_django/templates/eucaptcha/full_widget.html
myra_eucaptcha_django/templates/eucaptcha/widget.html
myra_eucaptcha_django/templatetags/__init__.py
myra_eucaptcha_django/templatetags/eucaptcha.py
myra_eucaptcha_django-0.1.0.dist-info/licenses/LICENSE
myra_eucaptcha_django-0.1.0.dist-info/METADATA
myra_eucaptcha_django-0.1.0.dist-info/WHEEL
myra_eucaptcha_django-0.1.0.dist-info/top_level.txt
myra_eucaptcha_django-0.1.0.dist-info/RECORD
