Metadata-Version: 2.4
Name: myra-eucaptcha-django
Version: 0.1.0
Summary: Django integration for Myra EU Captcha
Author-email: Myra Security GmbH <info@myrasecurity.com>
License: Copyright 2026 Myra Security GmbH
Project-URL: Homepage, https://www.eu-captcha.eu/
Project-URL: Documentation, https://docs.eu-captcha.eu/
Classifier: Development Status :: 5 - Production/Stable
Classifier: Framework :: Django
Classifier: Framework :: Django :: 4.2
Classifier: Framework :: Django :: 5.0
Classifier: Intended Audience :: Developers
Classifier: License :: Other/Proprietary License
Classifier: Programming Language :: Python :: 3
Classifier: Programming Language :: Python :: 3.9
Classifier: Programming Language :: Python :: 3.10
Classifier: Programming Language :: Python :: 3.11
Classifier: Programming Language :: Python :: 3.12
Classifier: Programming Language :: Python :: 3.13
Classifier: Topic :: Security
Requires-Python: >=3.9
License-File: LICENSE
Requires-Dist: myra-eucaptcha>=0.1.5
Requires-Dist: django>=4.2
Dynamic: license-file
